cmake_setuptools_ext/__init__.py
cmake_setuptools_ext/cmake_ext.py
cmake_setuptools_ext-0.1.2.dist-info/LICENSE
cmake_setuptools_ext-0.1.2.dist-info/METADATA
cmake_setuptools_ext-0.1.2.dist-info/WHEEL
cmake_setuptools_ext-0.1.2.dist-info/top_level.txt
cmake_setuptools_ext-0.1.2.dist-info/zip-safe
cmake_setuptools_ext-0.1.2.dist-info/RECORD
