Metadata-Version: 2.1
Name: cmake-setuptools-ext
Version: 0.1.2
Summary: An extension for setuptools when building Python/cmake projects
Home-page: https://github.com/vanandrew/cmake-setuptools-ext
Author: Andrew Van
Author-email: vanandrew@wustl.edu
License-File: LICENSE
Provides-Extra: all
Requires-Dist: black (>=20.8b0) ; extra == 'all'
Requires-Dist: pytest (>=6.2.5) ; extra == 'all'
Requires-Dist: coverage (>=5.5) ; extra == 'all'
Requires-Dist: pytest-pycodestyle (>=2.2.0) ; extra == 'all'
Provides-Extra: dev
Requires-Dist: black (>=20.8b0) ; extra == 'dev'
Requires-Dist: pytest (>=6.2.5) ; extra == 'dev'
Requires-Dist: coverage (>=5.5) ; extra == 'dev'
Requires-Dist: pytest-pycodestyle (>=2.2.0) ; extra == 'dev'
